{"en": {"Eerie Presence": {"card_desc": "[Mending Spirits] Reduce the Cooldown of Mending Spirits by {scale=0.5|0.5}s if you miss.", "card_cd": 0, "card_name_en": "Eerie Presence"}, "Feed the Spirits": {"card_desc": "[Armor] Reduce your active Cooldowns by {scale=10|10}% after getting an Elimination.", "card_cd": 0, "card_name_en": "Feed the Spirits"}, "Fleeting": {"card_desc": "[Slither] Reduce the Cooldown of Slither by {scale=0.6|0.6}s.", "card_cd": 0, "card_name_en": "Fleeting"}, "Incorporeal": {"card_desc": "[Armor] Increase your maximum Health by {scale=50|50}.", "card_cd": 0, "card_name_en": "Incorporeal"}, "Lighter Gourd": {"card_desc": "[Gourd] Increase the Projectile Speed of Gourd by {scale=10|10}%.", "card_cd": 0, "card_name_en": "Lighter Gourd"}, "Liminal Passage": {"card_desc": "[Slither] Increase the travel distance of Slither by {scale=10|10}%.", "card_cd": 0, "card_name_en": "Liminal Passage"}, "Many Gourds": {"card_desc": "[Gourd] Reduce the Cooldown of Gourd by {scale=0.5|0.5}s.", "card_cd": 0, "card_name_en": "Many Gourds"}, "Otherworldly": {"card_desc": "[Slither] Gain a {scale=75|75}-health Shield for 3s after Slither ends.", "card_cd": 0, "card_name_en": "Otherworldly"}, "Possession": {"card_desc": "[Mending Spirits] Reduce your damage taken by {scale=4|4}% while Healing an ally with Mending Spirits.", "card_cd": 0, "card_name_en": "Possession"}, "Pungent Gourd": {"card_desc": "[Gourd] Heal for {scale=75|75} after activating Gourd.", "card_cd": 0, "card_name_en": "Pungent Gourd"}, "Ripened Gourd": {"card_desc": "[Mending Spirits] Your Gourd no longer damages enemies, but it Heals for twice as much.", "card_cd": 0, "card_name_en": "Ripened Gourd"}, "Ritual Magic": {"card_desc": "[Mending Spirits] Heal for {scale=15|15} every 1s while Healing an ally with Mending Spirits.", "card_cd": 0, "card_name_en": "Ritual Magic"}, "Snake Pit": {"card_desc": "[Armor] Increase your Movement Speed by {scale=2|2}%.", "card_cd": 0, "card_name_en": "Snake Pit"}, "Spirit's Chosen": {"card_desc": "[Mending Spirits] Mending Spirits immediately Heals your target for an additional 200.", "card_cd": 0, "card_name_en": "Spirit's Chosen"}, "Spirit's Touch": {"card_desc": "[Slither] Heal for {scale=80|80} after using Slither.", "card_cd": 0, "card_name_en": "Spirit's Touch"}, "Sustenance": {"card_desc": "[Armor] Increase your Healing received by {scale=8|8}% while at or below 50% Health.", "card_cd": 0, "card_name_en": "Sustenance"}, "Swift Spirits": {"card_desc": "[Mending Spirits] Increase the Movement Speed of allies affected by Mending Spirits by {scale=5|5}%.", "card_cd": 0, "card_name_en": "Swift Spirits"}, "Venomous Gourd": {"card_desc": "[Gourd] Standing in your Gourd grants yourself and allies {scale=6|6}% Lifesteal.", "card_cd": 0, "card_name_en": "Venomous Gourd"}, "Wekono's Wrath": {"card_desc": "[Weapon] Tossing your snake after reloading is faster and deals an additional 500 damage.", "card_cd": 0, "card_name_en": "Wekono's Wrath"}}, "de": {"Bote der Geister": {"card_desc": "[Heilende Geister] Heilende Geister heilt direkt zus\u00e4tzliche 200 LP.", "card_cd": 0, "card_name_en": "Spirit's Chosen"}, "Faulige Kalebasse": {"card_desc": "[Kalebasse] Nach Aktivierung von Kalebasse wirst du {scale=75|75} LP geheilt.", "card_cd": 0, "card_name_en": "Pungent Gourd"}, "Flinke Geister": {"card_desc": "[Heilende Geister] Erh\u00f6ht das Lauftempo von Verb\u00fcndeten um {scale=5|5}%, w\u00e4hrend sie mit Heilende Geister geheilt werden.", "card_cd": 0, "card_name_en": "Swift Spirits"}, "Fl\u00fcchtig": {"card_desc": "[Schl\u00e4ngeln] Reduziert die Abklingzeit von Schl\u00e4ngeln um {scale=0.6|0.6}s.", "card_cd": 0, "card_name_en": "Fleeting"}, "Geisterhand": {"card_desc": "[Schl\u00e4ngeln] Nach Verwendung von Schl\u00e4ngeln wirst du {scale=80|80} LP geheilt.", "card_cd": 0, "card_name_en": "Spirit's Touch"}, "Geistermahl": {"card_desc": "[R\u00fcstung] Eliminierungen reduzieren alle aktiven Abklingzeiten um {scale=10|10}%.", "card_cd": 0, "card_name_en": "Feed the Spirits"}, "Gereifte Kalebasse": {"card_desc": "[Heilende Geister] Kalebasse f\u00fcgt Gegnern keinen Schaden mehr zu, heilt aber daf\u00fcr doppelt so viel.", "card_cd": 0, "card_name_en": "Ripened Gourd"}, "Giftige Kalebasse": {"card_desc": "[Kalebasse] Innerhalb des Gebiets von Kalebasse erhalten du und Verb\u00fcndete {scale=6|6}% Lebensraub.", "card_cd": 0, "card_name_en": "Venomous Gourd"}, "Jenseits": {"card_desc": "[Schl\u00e4ngeln] Wenn Schl\u00e4ngeln endet, erh\u00e4ltst du einen 3s lang einen Schild mit {scale=75|75} LP.", "card_cd": 0, "card_name_en": "Otherworldly"}, "K\u00f6rperlos": {"card_desc": "[R\u00fcstung] Erh\u00f6ht deine maximale Gesundheit um {scale=50|50} LP.", "card_cd": 0, "card_name_en": "Incorporeal"}, "Leichte Kalebasse": {"card_desc": "[Kalebasse] Erh\u00f6ht das Geschosstempo von Kalebasse um {scale=10|10}%.", "card_cd": 0, "card_name_en": "Lighter Gourd"}, "Ritualmagie": {"card_desc": "[Heilende Geister] W\u00e4hrend du einen Verb\u00fcndeten mit Heilende Geister heilst, wirst du {scale=15|15} LP pro Sekunde geheilt.", "card_cd": 0, "card_name_en": "Ritual Magic"}, "S\u00e4ttigung": {"card_desc": "[R\u00fcstung] Bei 50% oder weniger Gesundheit erh\u00e4ltst du um {scale=8|8}% erh\u00f6hte Heilung.", "card_cd": 0, "card_name_en": "Sustenance"}, "Schaurige Pr\u00e4senz": {"card_desc": "[Heilende Geister] Reduziert die Abklingzeit von Heilende Geister um {scale=0.5|0.5}s, wenn du nicht triffst.", "card_cd": 0, "card_name_en": "Eerie Presence"}, "Schlangengrube": {"card_desc": "[R\u00fcstung] Erh\u00f6ht dein Lauftempo um {scale=2|2}%.", "card_cd": 0, "card_name_en": "Snake Pit"}, "Schwellengang": {"card_desc": "[Schl\u00e4ngeln] Erh\u00f6ht die Reichweite von Schl\u00e4ngeln um {scale=10|10}%.", "card_cd": 0, "card_name_en": "Liminal Passage"}, "\u00dcbernahme": {"card_desc": "[Heilende Geister] W\u00e4hrend du einen Verb\u00fcndeten mit Heilende Geister heilst, wird von dir erlittener Schaden um {scale=4|4}% reduziert.", "card_cd": 0, "card_name_en": "Possession"}, "Viele Kalebassen": {"card_desc": "[Kalebasse] Reduziert die Abklingzeit von Kalebasse um {scale=0.5|0.5}s.", "card_cd": 0, "card_name_en": "Many Gourds"}, "Zorn des Wekono": {"card_desc": "[Waffe] Das Werfen der Schlange beim Nachladen geschieht schneller und verursacht 500 Bonusschaden.", "card_cd": 0, "card_name_en": "Wekono's Wrath"}}, "fr": {"Autre monde": {"card_desc": "[Serpenter] Serpenter g\u00e9n\u00e8re un bouclier de {scale=75|75} PV qui dure 3s.", "card_cd": 0, "card_name_en": "Otherworldly"}, "Courroux de Wekono": {"card_desc": "[Arme] Le lancer de serpent apr\u00e8s un rechargement est plus rapide et inflige 500 d\u00e9g\u00e2ts de plus.", "card_cd": 0, "card_name_en": "Wekono's Wrath"}, "\u00c9chapp\u00e9e": {"card_desc": "[Serpenter] La distance parcourue lors de Serpenter augmente de {scale=10|10}%.", "card_cd": 0, "card_name_en": "Liminal Passage"}, "\u00c9lu des esprits": {"card_desc": "[Esprit soigneur] Esprit soigneur redonne instantan\u00e9ment 200 PV de plus.", "card_cd": 0, "card_name_en": "Spirit's Chosen"}, "Esprits repus": {"card_desc": "[Armure] Chaque \u00e9limination r\u00e9duit les temps de recharge en cours de {scale=10|10}%.", "card_cd": 0, "card_name_en": "Feed the Spirits"}, "Esprits vifs": {"card_desc": "[Esprit soigneur] Esprit soigneur octroie {scale=5|5}% de vitesse aux alli\u00e9s atteints.", "card_cd": 0, "card_name_en": "Swift Spirits"}, "\u00c9th\u00e9r\u00e9": {"card_desc": "[Armure] Vous avez {scale=50|50} PV de plus.", "card_cd": 0, "card_name_en": "Incorporeal"}, "Fosse \u00e0 serpents": {"card_desc": "[Arme/Armure] Votre vitesse augmente de {scale=2|2}%.", "card_cd": 0, "card_name_en": "Snake Pit"}, "Fugace": {"card_desc": "[Serpenter] Serpenter se recharge {scale=0.6|0.6}s plus vite.", "card_cd": 0, "card_name_en": "Fleeting"}, "Gourde \u00e0 venin": {"card_desc": "[Gourde] Dans la zone de Gourde, vous et vos alli\u00e9s avez {scale=6|6}% de drain de vie.", "card_cd": 0, "card_name_en": "Venomous Gourd"}, "Gourde l\u00e9g\u00e8re": {"card_desc": "[Gourde] La vitesse du projectile de Gourde augmente de {scale=10|10}%.", "card_cd": 0, "card_name_en": "Lighter Gourd"}, "Gourde puissante": {"card_desc": "[Gourde] Activer Gourde vous rend {scale=75|75} PV.", "card_cd": 0, "card_name_en": "Pungent Gourd"}, "Gourde trop m\u00fbre": {"card_desc": "[Esprit soigneur] La Gourde rend deux fois plus de PV mais n'inflige plus aucun d\u00e9g\u00e2t.", "card_cd": 0, "card_name_en": "Ripened Gourd"}, "Gourdes \u00e0 gogo": {"card_desc": "[Gourde] Gourde se recharge {scale=0.5|0.5}s plus vite.", "card_cd": 0, "card_name_en": "Many Gourds"}, "Magie rituelle": {"card_desc": "[Esprit soigneur] Vous r\u00e9cup\u00e9rez {scale=15|15} PV/s tant que vous soignez un alli\u00e9 avec Esprit soigneur.", "card_cd": 0, "card_name_en": "Ritual Magic"}, "Possession": {"card_desc": "[Esprit soigneur] Vous subissez {scale=4|4}% de d\u00e9g\u00e2ts en moins tant que vous soignez un alli\u00e9 avec Esprit soigneur.", "card_cd": 0, "card_name_en": "Possession"}, "Subsistance": {"card_desc": "[Armure] En dessous de 50% de PV, vous recevez {scale=8|8}% de soins en plus.", "card_cd": 0, "card_name_en": "Sustenance"}, "Surnaturel": {"card_desc": "[Esprit soigneur] Esprit soigneur se recharge {scale=0.5|0.5}s plus vite quand vous ratez votre coup.", "card_cd": 0, "card_name_en": "Eerie Presence"}, "Toucher spirituel": {"card_desc": "[Serpenter] Serpenter vous redonne {scale=80|80} PV.", "card_cd": 0, "card_name_en": "Spirit's Touch"}}, "zh": {"\u4eea\u5f0f\u9b54\u6cd5I": {"card_desc": "[\u6062\u590d\u4e4b\u7075] \u7528\u6062\u590d\u4e4b\u7075\u6cbb\u7597\u76ee\u6807\u65f6\u81ea\u8eab\u4e5f\u4f1a\u6bcf\u79d2\u56de\u590d{scale=15|15}\u70b9\u751f\u547d\u503c", "card_cd": 0, "card_name_en": "Ritual Magic"}, "\u523a\u9f3b\u846b\u82a6": {"card_desc": "[\u5deb\u6bd2\u846b\u82a6] \u5deb\u6bd2\u846b\u82a6\u547d\u4e2d\u654c\u4eba\u540e\u4f1a\u4f7f\u654c\u65b9\u663e\u5f62\uff0c\u6301\u7eed{scale=0.8|0.8}\u79d2", "card_cd": 0, "card_name_en": "Pungent Gourd"}, "\u5267\u6bd2\u846b\u82a6I": {"card_desc": "[\u5deb\u6bd2\u846b\u82a6] \u88ab\u5deb\u6bd2\u846b\u82a6\u547d\u4e2d\u7684\u654c\u4eba\u53d7\u5230\u7684\u6cbb\u7597\u6548\u679c\u964d\u4f4e{scale=10|10}%\uff0c\u6301\u7eed3\u79d2", "card_cd": 0, "card_name_en": "Venomous Gourd"}, "\u591a\u91cd\u846b\u82a6I": {"card_desc": "[\u5deb\u6bd2\u846b\u82a6] \u964d\u4f4e\u5deb\u6bd2\u846b\u82a6\u7684\u51b7\u5374\u65f6\u95f4{scale=0.5|0.5}\u79d2", "card_cd": 0, "card_name_en": "Many Gourds"}, "\u5929\u9009\u4e4b\u4eba": {"card_desc": "[\u6062\u590d\u4e4b\u7075] \u6062\u590d\u4e4b\u7075\u4f1a\u7acb\u5373\u4e3a\u76ee\u6807\u56de\u590d300\u70b9\u751f\u547d\uff0c\u7136\u540e\u518d\u9644\u52a0\u540e\u7eed\u6cbb\u7597\u6548\u679c", "card_cd": 0, "card_name_en": "Spirit's Chosen"}, "\u6050\u6016\u5316\u8eab": {"card_desc": "[\u6062\u590d\u4e4b\u7075] \u6280\u80fd\u672a\u547d\u4e2d\u76ee\u6807\u65f6\uff0c\u51b7\u5374\u65f6\u95f4\u964d\u4f4e{scale=0.5|0.5}\u79d2", "card_cd": 0, "card_name_en": "Eerie Presence"}, "\u6301\u7eed\u8865\u7ed9I": {"card_desc": "[\u62a4\u7532] \u751f\u547d\u503c\u4f4e\u4e8e50%\u65f6\u83b7\u5f97\u7684\u6cbb\u7597\u6548\u679c\u63d0\u9ad8{scale=8|8}%", "card_cd": 0, "card_name_en": "Sustenance"}, "\u6781\u9650\u901a\u9053I": {"card_desc": "[\u86c7\u884c\u7a81\u8fdb] \u7a81\u8fdb\u8ddd\u79bb\u63d0\u9ad8 {scale=10|10}%", "card_cd": 0, "card_name_en": "Liminal Passage"}, "\u865a\u65e0\u7075\u4f53I": {"card_desc": "[\u62a4\u7532] \u6700\u5927\u751f\u547d\u503c\u63d0\u9ad8{scale=50|50}\u70b9", "card_cd": 0, "card_name_en": "Incorporeal"}, "\u86c7\u5751I": {"card_desc": "[\u6b66\u5668] \u88c5\u586b\u901f\u5ea6\u63d0\u9ad8{scale=5|5}%", "card_cd": 0, "card_name_en": "Snake Pit"}, "\u86c7\u7075\u4e4b\u6012": {"card_desc": "[\u6b66\u5668] \u6bd2\u86c7\u6295\u63b7\u9020\u6210\u989d\u5916500\u70b9\u4f24\u5bb3", "card_cd": 0, "card_name_en": "Wekono's Wrath"}, "\u86c7\u7075\u4e4b\u89e6I": {"card_desc": "[\u86c7\u884c\u7a81\u8fdb] \u6fc0\u6d3b\u86c7\u884c\u7a81\u8fdb\u4f1a\u56de\u590d{scale=50|50}\u70b9\u751f\u547d\u503c", "card_cd": 0, "card_name_en": "Spirit's Touch"}, "\u86c7\u7075\u796d\u54c1I": {"card_desc": "[\u62a4\u7532] \u51fb\u8d25\u654c\u4eba\u6216\u52a9\u653b\u53ef\u4ee5\u4f7f\u6240\u6709\u4e3b\u52a8\u6280\u80fd\u7684\u51b7\u5374\u65f6\u95f4\u964d\u4f4e{scale=10|10}%", "card_cd": 0, "card_name_en": "Feed the Spirits"}, "\u86c7\u7075\u8bc5\u5492": {"card_desc": "[\u6062\u590d\u4e4b\u7075] \u6062\u590d\u4e4b\u7075\u73b0\u5728\u53ef\u5bf9\u654c\u4eba\u4f7f\u7528\uff0c2\u79d2\u5185\u9020\u6210560\u70b9\u4f24\u5bb3", "card_cd": 0, "card_name_en": "Ripened Gourd"}, "\u86c7\u7075\u9644\u8eabI": {"card_desc": "[\u6062\u590d\u4e4b\u7075] \u7528\u6062\u590d\u4e4b\u7075\u6cbb\u7597\u76ee\u6807\u65f6\u83b7\u5f97{scale=4|4}%\u7684\u4f24\u5bb3\u51cf\u514d", "card_cd": 0, "card_name_en": "Possession"}, "\u8d85\u51e1I": {"card_desc": "[\u86c7\u884c\u7a81\u8fdb] \u7a81\u8fdb\u7ed3\u675f\u540e\u63d0\u9ad8{scale=10|10}%\u7684\u79fb\u52a8\u901f\u5ea6\uff0c\u6301\u7eed3\u79d2", "card_cd": 0, "card_name_en": "Otherworldly"}, "\u8f7b\u8d28\u846b\u82a6I": {"card_desc": "[\u5deb\u6bd2\u846b\u82a6] \u846b\u82a6\u7684\u6295\u63b7\u901f\u5ea6\u63d0\u9ad8{scale=10|10}%", "card_cd": 0, "card_name_en": "Lighter Gourd"}, "\u8fc5\u6377\u4e4b\u7075I": {"card_desc": "[\u6062\u590d\u4e4b\u7075] \u4f7f\u7528\u6062\u590d\u4e4b\u7075\u6cbb\u7597\u76ee\u6807\u540e\u4e5f\u4f1a\u63d0\u9ad8\u76ee\u6807{scale=7|7}%\u7684\u79fb\u52a8\u901f\u5ea6", "card_cd": 0, "card_name_en": "Swift Spirits"}, "\u98de\u901dI": {"card_desc": "[\u86c7\u884c\u7a81\u8fdb] \u86c7\u884c\u7a81\u8fdb\u7684\u51b7\u5374\u65f6\u95f4\u964d\u4f4e{scale=0.5|0.5}\u79d2", "card_cd": 0, "card_name_en": "Fleeting"}}, "od": {}, "es": {"Alimento espiritual": {"card_desc": "[Armadura] Tus recargas activas se reducen un {scale=10|10}% tras conseguir una eliminaci\u00f3n.", "card_cd": 0, "card_name_en": "Feed the Spirits"}, "Elegido por los esp\u00edritus": {"card_desc": "[Esp\u00edritus sanadores] Esp\u00edritus sanadores cura 200 PS m\u00e1s al objetivo instant\u00e1neamente.", "card_cd": 0, "card_name_en": "Spirit's Chosen"}, "Esp\u00edritus raudos": {"card_desc": "[Esp\u00edritus sanadores] La velocidad de movimiento de los aliados afectados por Esp\u00edritus sanadores aumenta un {scale=5|5}%.", "card_cd": 0, "card_name_en": "Swift Spirits"}, "Fugacidad": {"card_desc": "[Serpenteo] Se reduce la recarga de Serpenteo en {scale=0.6|0.6}s.", "card_cd": 0, "card_name_en": "Fleeting"}, "Incorp\u00f3reo": {"card_desc": "[Armadura] Tu salud m\u00e1xima aumenta en {scale=50|50} PS.", "card_cd": 0, "card_name_en": "Incorporeal"}, "Ira de Wekono": {"card_desc": "[Arma] Tiras tu serpiente tras recargar m\u00e1s r\u00e1pido e infliges 500 PS de da\u00f1o adicionales.", "card_cd": 0, "card_name_en": "Wekono's Wrath"}, "J\u00edcara acre": {"card_desc": "[J\u00edcara] Te curas {scale=75|75} PS tras activar J\u00edcara.", "card_cd": 0, "card_name_en": "Pungent Gourd"}, "J\u00edcara \u00e1gil": {"card_desc": "[J\u00edcara] La velocidad de proyectil de J\u00edcara aumenta un {scale=10|10}%.", "card_cd": 0, "card_name_en": "Lighter Gourd"}, "J\u00edcara madura": {"card_desc": "[Esp\u00edritus sanadores] Tu j\u00edcara ya no da\u00f1a a los enemigos, pero cura el doble.", "card_cd": 0, "card_name_en": "Ripened Gourd"}, "J\u00edcara venenosa": {"card_desc": "[J\u00edcara] Si te quedas dentro de tu J\u00edcara, t\u00fa y tus aliados reciben un {scale=6|6}% de robo de vida.", "card_cd": 0, "card_name_en": "Venomous Gourd"}, "J\u00edcaras m\u00faltiples": {"card_desc": "[J\u00edcara] Se reduce la recarga de J\u00edcara en {scale=0.5|0.5}s.", "card_cd": 0, "card_name_en": "Many Gourds"}, "Pasaje liminal": {"card_desc": "[Serpenteo] La distancia que puede recorrer Serpenteo aumenta un {scale=10|10}%.", "card_cd": 0, "card_name_en": "Liminal Passage"}, "Posesi\u00f3n": {"card_desc": "[Esp\u00edritus sanadores] Se reduce el da\u00f1o recibido un {scale=4|4}% mientras curas a un aliado con Esp\u00edritus sanadores.", "card_cd": 0, "card_name_en": "Possession"}, "Presencia inquietante": {"card_desc": "[Esp\u00edritus sanadores] Se reduce la recarga de Esp\u00edritus sanadores en {scale=0.5|0.5}s si no aciertas.", "card_cd": 0, "card_name_en": "Eerie Presence"}, "Ritual m\u00e1gico": {"card_desc": "[Esp\u00edritus sanadores] Te curas {scale=15|15} PS cada 1s mientras curas a un aliado con Esp\u00edritus sanadores.", "card_cd": 0, "card_name_en": "Ritual Magic"}, "Roce espiritual": {"card_desc": "[Serpenteo] Te curas {scale=80|80} PS tras usar Serpenteo.", "card_cd": 0, "card_name_en": "Spirit's Touch"}, "Sobrenatural": {"card_desc": "[Serpenteo] Ganas un escudo de {scale=75|75} PS durante 3s despu\u00e9s de que acabe Serpento.", "card_cd": 0, "card_name_en": "Otherworldly"}, "Sustento": {"card_desc": "[Armadura] La curaci\u00f3n que recibes aumenta un {scale=8|8}% si tienes un 50% o menos de salud.", "card_cd": 0, "card_name_en": "Sustenance"}, "Trampa serpentina": {"card_desc": "[Armadura] Tu velocidad de movimiento aumenta un {scale=2|2}%.", "card_cd": 0, "card_name_en": "Snake Pit"}}, "pt": {"Alimente os Esp\u00edritos": {"card_desc": "[Armadura] Reduz em {scale=10|10}% todos os intervalos ativos ao conseguir uma elimina\u00e7\u00e3o.", "card_cd": 0, "card_name_en": "Feed the Spirits"}, "Caba\u00e7a Leve": {"card_desc": "[Caba\u00e7a] Aumenta em {scale=10|10}% a velocidade de arremesso da Caba\u00e7a.", "card_cd": 0, "card_name_en": "Lighter Gourd"}, "Caba\u00e7a Madura": {"card_desc": "[Esp\u00edrito de Cura] Sua Caba\u00e7a n\u00e3o causa mais dano nos inimigos, mas concede o dobro de cura.", "card_cd": 0, "card_name_en": "Ripened Gourd"}, "Caba\u00e7a Pungente": {"card_desc": "[Caba\u00e7a] Voc\u00ea se cura em {scale=75|75} de vida ap\u00f3s arremessar a Caba\u00e7a.", "card_cd": 0, "card_name_en": "Pungent Gourd"}, "Caba\u00e7as Venenosas": {"card_desc": "Caba\u00e7a] Voc\u00ea e seus aliados ganham {scale=6|6}% de roubo de vida enquanto estiverem sobre a \u00e1rea da Caba\u00e7a", "card_cd": 0, "card_name_en": "Venomous Gourd"}, "Escolhido dos Esp\u00edritos": {"card_desc": "[Esp\u00edrito de Cura] Esp\u00edrito de Cura imediatamente cura um adicional de 200 de vida.", "card_cd": 0, "card_name_en": "Spirit's Chosen"}, "Esp\u00edritos Velozes": {"card_desc": "[Esp\u00edrito de Cura] Aumenta em {scale=5|5}% a velocidade de movimento dos aliados afetados pelo Esp\u00edrito de Cura.", "card_cd": 0, "card_name_en": "Swift Spirits"}, "Fugaz": {"card_desc": "[Deslizar] Reduz o intervalo de Deslizar em {scale=0.6|0.6}s.", "card_cd": 0, "card_name_en": "Fleeting"}, "Incorp\u00f3reo": {"card_desc": "[Armadura] Aumenta a sua vida m\u00e1xima em {scale=50|50}.", "card_cd": 0, "card_name_en": "Incorporeal"}, "Ira de Wekono": {"card_desc": "[Arma] O arremesso da cobra ap\u00f3s recarregar a arma \u00e9 mais r\u00e1pido e causa dano adicional de 500.", "card_cd": 0, "card_name_en": "Wekono's Wrath"}, "Magia Ritual\u00edstica": {"card_desc": "[Esp\u00edrito de Cura] Voc\u00ea se cura em {scale=15|15} de vida a cada 1s enquanto Esp\u00edrito de Cura estiver curando um aliado.", "card_cd": 0, "card_name_en": "Ritual Magic"}, "Passando na Frente": {"card_desc": "[Deslizar] Aumenta a dist\u00e2ncia que Deslizar percorre em {scale=10|10}%.", "card_cd": 0, "card_name_en": "Liminal Passage"}, "Po\u00e7o de Cobras": {"card_desc": "[Armadura] Aumenta sua velocidade de movimento em {scale=2|2}%.", "card_cd": 0, "card_name_en": "Snake Pit"}, "Possess\u00e3o": {"card_desc": "[Esp\u00edrito de Cura] Voc\u00ea ganha {scale=4|4}% de redu\u00e7\u00e3o de dano enquanto um aliado \u00e9 curado pelo Esp\u00edrito de Cura.", "card_cd": 0, "card_name_en": "Possession"}, "Presen\u00e7a Arrepiante": {"card_desc": "[Esp\u00edrito de Cura] Reduz o intervalo de Esp\u00edrito de Cura em {scale=0.5|0.5}s caso voc\u00ea erre.", "card_cd": 0, "card_name_en": "Eerie Presence"}, "Sustento": {"card_desc": "[Armadura] Aumenta a cura recebida em {scale=8|8}% enquanto estiver com 50% ou menos de vida.", "card_cd": 0, "card_name_en": "Sustenance"}, "Toque do Esp\u00edrito": {"card_desc": "[Deslizar] Voc\u00ea se cura em {scale=80|80} de vida ap\u00f3s usar Deslizar.", "card_cd": 0, "card_name_en": "Spirit's Touch"}, "Transcendental": {"card_desc": "[Deslizar] Ganha um escudo de {scale=75|75} por 3s ap\u00f3s concluir Deslizar.", "card_cd": 0, "card_name_en": "Otherworldly"}, "V\u00e1rias Caba\u00e7as": {"card_desc": "[Caba\u00e7a] Reduz o intervalo da Caba\u00e7a em {scale=0.5|0.5}s.", "card_cd": 0, "card_name_en": "Many Gourds"}}, "ru": {"\u0411\u0435\u0441\u0442\u0435\u043b\u0435\u0441\u043d\u043e\u0441\u0442\u044c": {"card_desc": "[\u0411\u0440\u043e\u043d\u044f] \u0412\u0430\u0448\u0435 \u043c\u0430\u043a\u0441\u0438\u043c\u0430\u043b\u044c\u043d\u043e\u0435 \u0437\u0434\u043e\u0440\u043e\u0432\u044c\u0435 \u043f\u043e\u0432\u044b\u0448\u0430\u0435\u0442\u0441\u044f \u043d\u0430 {scale=50|50} \u0435\u0434.", "card_cd": 0, "card_name_en": "Incorporeal"}, "\u0413\u043d\u0435\u0432 \u0412\u0435\u043a\u043e\u043d\u043e": {"card_desc": "[\u041e\u0440\u0443\u0436\u0438\u0435] \u0417\u043c\u0435\u0438\u043d\u044b\u0439 \u0431\u0440\u043e\u0441\u043e\u043a \u043f\u043e\u0441\u043b\u0435 \u043f\u0435\u0440\u0435\u0437\u0430\u0440\u044f\u0434\u043a\u0438 \u0441\u0442\u0430\u043d\u043e\u0432\u0438\u0442\u0441\u044f \u0431\u044b\u0441\u0442\u0440\u0435\u0435 \u0438 \u043d\u0430\u043d\u043e\u0441\u0438\u0442 \u043d\u0430 500 \u0435\u0434. \u0431\u043e\u043b\u044c\u0448\u0435 \u0443\u0440\u043e\u043d\u0430.", "card_cd": 0, "card_name_en": "Wekono's Wrath"}, "\u0416\u0443\u0442\u043a\u043e\u0435 \u043f\u0440\u0438\u0441\u0443\u0442\u0441\u0442\u0432\u0438\u0435": {"card_desc": "[\u0414\u0443\u0445 \u0446\u0435\u043b\u0438\u0442\u0435\u043b\u044f] \u041f\u0440\u043e\u043c\u0430\u0445\u0438 \u0441\u043e\u043a\u0440\u0430\u0449\u0430\u044e\u0442 \u043f\u0435\u0440\u0435\u0437\u0430\u0440\u044f\u0434\u043a\u0443 \u0414\u0443\u0445\u0430 \u0446\u0435\u043b\u0438\u0442\u0435\u043b\u044f \u043d\u0430 {scale=0.5|0.5} \u0441.", "card_cd": 0, "card_name_en": "Eerie Presence"}, "\u0417\u043c\u0435\u0438\u043d\u0430\u044f \u044f\u043c\u0430": {"card_desc": "[\u0411\u0440\u043e\u043d\u044f] \u0412\u0430\u0448\u0430 \u0441\u043a\u043e\u0440\u043e\u0441\u0442\u044c \u043f\u0435\u0440\u0435\u0434\u0432\u0438\u0436\u0435\u043d\u0438\u044f \u043f\u043e\u0432\u044b\u0448\u0430\u0435\u0442\u0441\u044f \u043d\u0430 {scale=2|2}%.", "card_cd": 0, "card_name_en": "Snake Pit"}, "\u0417\u0440\u0435\u043b\u0430\u044f \u0442\u044b\u043a\u0432\u0430": {"card_desc": "[\u0414\u0443\u0445 \u0446\u0435\u043b\u0438\u0442\u0435\u043b\u044f] \u0422\u044b\u043a\u0432\u0430 \u0431\u043e\u043b\u044c\u0448\u0435 \u043d\u0435 \u043d\u0430\u043d\u043e\u0441\u0438\u0442 \u0432\u0440\u0430\u0433\u0430\u043c \u0443\u0440\u043e\u043d\u0430, \u043d\u043e \u0435\u0435 \u044d\u0444\u0444\u0435\u043a\u0442 \u0438\u0441\u0446\u0435\u043b\u0435\u043d\u0438\u044f \u0443\u0434\u0432\u043e\u0435\u043d.", "card_cd": 0, "card_name_en": "Ripened Gourd"}, "\u0418\u0437\u0431\u0440\u0430\u043d\u043d\u0438\u043a \u0434\u0443\u0445\u0430": {"card_desc": "[\u0414\u0443\u0445 \u0446\u0435\u043b\u0438\u0442\u0435\u043b\u044f] \u0414\u0443\u0445 \u0446\u0435\u043b\u0438\u0442\u0435\u043b\u044f \u043c\u0433\u043d\u043e\u0432\u0435\u043d\u043d\u043e \u0438\u0441\u0446\u0435\u043b\u044f\u0435\u0442 \u0432\u044b\u0431\u0440\u0430\u043d\u043d\u0443\u044e \u0446\u0435\u043b\u044c \u0435\u0449\u0435 \u043d\u0430 200 \u0435\u0434.", "card_cd": 0, "card_name_en": "Spirit's Chosen"}, "\u041a\u0430\u0441\u0430\u043d\u0438\u0435 \u0434\u0443\u0445\u0430": {"card_desc": "[\u041f\u0440\u0435\u0441\u043c\u044b\u043a\u0430\u044e\u0449\u0435\u0435\u0441\u044f] \u041f\u043e\u0441\u043b\u0435 \u0438\u0441\u043f\u043e\u043b\u044c\u0437\u043e\u0432\u0430\u043d\u0438\u044f \u041f\u0440\u0435\u0441\u043c\u044b\u043a\u0430\u044e\u0449\u0435\u0433\u043e\u0441\u044f \u0432\u044b \u0438\u0441\u0446\u0435\u043b\u044f\u0435\u0442\u0435\u0441\u044c \u043d\u0430 {scale=80|80} \u0435\u0434.", "card_cd": 0, "card_name_en": "Spirit's Touch"}, "\u041b\u0435\u0433\u043a\u0430\u044f \u0442\u044b\u043a\u0432\u0430": {"card_desc": "[\u0422\u044b\u043a\u0432\u0430] \u0421\u043a\u043e\u0440\u043e\u0441\u0442\u044c \u0441\u043d\u0430\u0440\u044f\u0434\u0430 \u0422\u044b\u043a\u0432\u044b \u043f\u043e\u0432\u044b\u0448\u0430\u0435\u0442\u0441\u044f \u043d\u0430 {scale=10|10}%.", "card_cd": 0, "card_name_en": "Lighter Gourd"}, "\u041c\u0438\u043c\u043e\u043b\u0435\u0442\u043d\u043e\u0441\u0442\u044c": {"card_desc": "[\u041f\u0440\u0435\u0441\u043c\u044b\u043a\u0430\u044e\u0449\u0435\u0435\u0441\u044f] \u041f\u0435\u0440\u0435\u0437\u0430\u0440\u044f\u0434\u043a\u0430 \u041f\u0440\u0435\u0441\u043c\u044b\u043a\u0430\u044e\u0449\u0435\u0433\u043e\u0441\u044f \u0441\u043e\u043a\u0440\u0430\u0449\u0430\u0435\u0442\u0441\u044f \u043d\u0430 {scale=0.6|0.6} \u0441.", "card_cd": 0, "card_name_en": "Fleeting"}, "\u041c\u043d\u043e\u0433\u043e \u0442\u044b\u043a\u0432": {"card_desc": "[\u0422\u044b\u043a\u0432\u0430] \u041f\u0435\u0440\u0435\u0437\u0430\u0440\u044f\u0434\u043a\u0430 \u0422\u044b\u043a\u0432\u044b \u0441\u043e\u043a\u0440\u0430\u0449\u0430\u0435\u0442\u0441\u044f \u043d\u0430 {scale=0.5|0.5} \u0441.", "card_cd": 0, "card_name_en": "Many Gourds"}, "\u041d\u0430\u043a\u043e\u0440\u043c\u0438 \u0434\u0443\u0445\u043e\u0432": {"card_desc": "[\u0411\u0440\u043e\u043d\u044f] \u0423\u0441\u0442\u0440\u0430\u043d\u0435\u043d\u0438\u044f \u0441\u043e\u043a\u0440\u0430\u0449\u0430\u044e\u0442 \u0442\u0435\u043a\u0443\u0449\u0443\u044e \u043f\u0435\u0440\u0435\u0437\u0430\u0440\u044f\u0434\u043a\u0443 \u0441\u043f\u043e\u0441\u043e\u0431\u043d\u043e\u0441\u0442\u0435\u0439 \u043d\u0430 {scale=10|10}%.", "card_cd": 0, "card_name_en": "Feed the Spirits"}, "\u041e\u0434\u0435\u0440\u0436\u0438\u043c\u043e\u0441\u0442\u044c": {"card_desc": "[\u0414\u0443\u0445 \u0446\u0435\u043b\u0438\u0442\u0435\u043b\u044f] \u0412\u044b \u043f\u043e\u043b\u0443\u0447\u0430\u0435\u0442\u0435 \u043d\u0430 {scale=4|4}% \u043c\u0435\u043d\u044c\u0448\u0435 \u0443\u0440\u043e\u043d\u0430 \u0432\u043e \u0432\u0440\u0435\u043c\u044f \u0438\u0441\u0446\u0435\u043b\u0435\u043d\u0438\u044f \u0441\u043e\u044e\u0437\u043d\u0438\u043a\u0430 \u0414\u0443\u0445\u043e\u043c \u0446\u0435\u043b\u0438\u0442\u0435\u043b\u044f.", "card_cd": 0, "card_name_en": "Possession"}, "\u041f\u0438\u043a\u0430\u043d\u0442\u043d\u0430\u044f \u0442\u044b\u043a\u0432\u0430": {"card_desc": "[\u0422\u044b\u043a\u0432\u0430] \u0410\u043a\u0442\u0438\u0432\u0430\u0446\u0438\u044f \u0422\u044b\u043a\u0432\u044b \u0438\u0441\u0446\u0435\u043b\u044f\u0435\u0442 \u0432\u0430\u0441 \u043d\u0430 {scale=75|75} \u0435\u0434.", "card_cd": 0, "card_name_en": "Pungent Gourd"}, "\u041f\u043e\u0434\u0434\u0435\u0440\u0436\u0430\u043d\u0438\u0435 \u0441\u0438\u043b": {"card_desc": "[\u0411\u0440\u043e\u043d\u044f] \u041f\u0440\u0438 \u0443\u0440\u043e\u0432\u043d\u0435 \u0437\u0434\u043e\u0440\u043e\u0432\u044c\u044f 50% \u0438 \u043d\u0438\u0436\u0435 \u0432\u044b \u043f\u043e\u043b\u0443\u0447\u0430\u0435\u0442\u0435 \u043d\u0430 {scale=8|8}% \u0431\u043e\u043b\u044c\u0448\u0435 \u0438\u0441\u0446\u0435\u043b\u0435\u043d\u0438\u044f.", "card_cd": 0, "card_name_en": "Sustenance"}, "\u041f\u043e\u0440\u043e\u0433\u043e\u0432\u044b\u0439 \u043f\u0435\u0440\u0435\u0445\u043e\u0434": {"card_desc": "[\u041f\u0440\u0435\u0441\u043c\u044b\u043a\u0430\u044e\u0449\u0435\u0435\u0441\u044f] \u0414\u0430\u043b\u044c\u043d\u043e\u0441\u0442\u044c \u043f\u0435\u0440\u0435\u043c\u0435\u0449\u0435\u043d\u0438\u044f \u041f\u0440\u0435\u0441\u043c\u044b\u043a\u0430\u044e\u0449\u0435\u0433\u043e\u0441\u044f \u0443\u0432\u0435\u043b\u0438\u0447\u0438\u0432\u0430\u0435\u0442\u0441\u044f \u043d\u0430 {scale=10|10}%.", "card_cd": 0, "card_name_en": "Liminal Passage"}, "\u041f\u043e\u0442\u0443\u0441\u0442\u043e\u0440\u043e\u043d\u043d\u0435\u0435": {"card_desc": "[\u041f\u0440\u0435\u0441\u043c\u044b\u043a\u0430\u044e\u0449\u0435\u0435\u0441\u044f] \u041f\u043e \u043e\u043a\u043e\u043d\u0447\u0430\u043d\u0438\u0438 \u0434\u0435\u0439\u0441\u0442\u0432\u0438\u044f \u041f\u0440\u0435\u0441\u043c\u044b\u043a\u0430\u044e\u0449\u0435\u0433\u043e\u0441\u044f \u0432\u044b \u043f\u043e\u043b\u0443\u0447\u0430\u0435\u0442\u0435 \u0449\u0438\u0442 \u043f\u0440\u043e\u0447\u043d\u043e\u0441\u0442\u044c\u044e {scale=75|75} \u0435\u0434. \u043d\u0430 3 \u0441.", "card_cd": 0, "card_name_en": "Otherworldly"}, "\u041f\u0440\u043e\u0432\u043e\u0440\u043d\u044b\u0435 \u0434\u0443\u0445\u0438": {"card_desc": "[\u0414\u0443\u0445 \u0446\u0435\u043b\u0438\u0442\u0435\u043b\u044f] \u0421\u043a\u043e\u0440\u043e\u0441\u0442\u044c \u043f\u0435\u0440\u0435\u0434\u0432\u0438\u0436\u0435\u043d\u0438\u044f \u0441\u043e\u044e\u0437\u043d\u0438\u043a\u043e\u0432 \u043f\u043e\u0434 \u0434\u0435\u0439\u0441\u0442\u0432\u0438\u0435\u043c \u0414\u0443\u0445\u0430 \u0446\u0435\u043b\u0438\u0442\u0435\u043b\u044f \u043f\u043e\u0432\u044b\u0448\u0430\u0435\u0442\u0441\u044f \u043d\u0430 {scale=5|5}%.", "card_cd": 0, "card_name_en": "Swift Spirits"}, "\u0420\u0438\u0442\u0443\u0430\u043b\u044c\u043d\u0430\u044f \u043c\u0430\u0433\u0438\u044f": {"card_desc": "[\u0414\u0443\u0445 \u0446\u0435\u043b\u0438\u0442\u0435\u043b\u044f] \u0412\u044b \u0438\u0441\u0446\u0435\u043b\u044f\u0435\u0442\u0435\u0441\u044c \u043d\u0430 {scale=15|15} \u0435\u0434. \u0432 \u0441\u0435\u043a\u0443\u043d\u0434\u0443 \u0432\u043e \u0432\u0440\u0435\u043c\u044f \u0438\u0441\u0446\u0435\u043b\u0435\u043d\u0438\u044f \u0441\u043e\u044e\u0437\u043d\u0438\u043a\u0430 \u0414\u0443\u0445\u043e\u043c \u0446\u0435\u043b\u0438\u0442\u0435\u043b\u044f.", "card_cd": 0, "card_name_en": "Ritual Magic"}, "\u042f\u0434\u043e\u0432\u0438\u0442\u0430\u044f \u0442\u044b\u043a\u0432\u0430": {"card_desc": "[\u0422\u044b\u043a\u0432\u0430] \u0412 \u043e\u0431\u043b\u0430\u0441\u0442\u0438 \u0434\u0435\u0439\u0441\u0442\u0432\u0438\u044f \u0422\u044b\u043a\u0432\u044b \u0432\u044b \u0438 \u0432\u0430\u0448\u0438 \u0441\u043e\u044e\u0437\u043d\u0438\u043a\u0438 \u043f\u043e\u043b\u0443\u0447\u0430\u0435\u0442\u0435 \u044d\u0444\u0444\u0435\u043a\u0442 \u0432\u0430\u043c\u043f\u0438\u0440\u0438\u0437\u043c\u0430 {scale=6|6}%.", "card_cd": 0, "card_name_en": "Venomous Gourd"}}, "pl": {"Bezcielesno\u015b\u0107": {"card_desc": "[Pancerz] Zwi\u0119ksza twoje maks. zdrowie o {scale=50|50} PZ.", "card_cd": 0, "card_name_en": "Incorporeal"}, "Dojrza\u0142a tykwa": {"card_desc": "[Duchy naprawcze] Twoja Tykwa nie zadaje ju\u017c obra\u017ce\u0144 wrogom, ale przywraca dwa razy wi\u0119cej PZ.", "card_cd": 0, "card_name_en": "Ripened Gourd"}, "Dotyk ducha": {"card_desc": "[\u015alizg] Przywraca ci {scale=80|80} PZ po u\u017cyciu \u015alizgu.", "card_cd": 0, "card_name_en": "Spirit's Touch"}, "Gniazdo w\u0119\u017ca": {"card_desc": "[Pancerz] Zwi\u0119ksza twoj\u0105 szybko\u015b\u0107 ruchu o {scale=2|2}%.", "card_cd": 0, "card_name_en": "Snake Pit"}, "Gniew Wekono": {"card_desc": "[Bro\u0144] Rzut w\u0119\u017cem po prze\u0142adowaniu jest szybszy i zadaje 500 dodatkowych obra\u017ce\u0144.", "card_cd": 0, "card_name_en": "Wekono's Wrath"}, "Karmienie duch\u00f3w": {"card_desc": "[Pancerz] Eliminacje skracaj\u0105 aktywne czasy odnowienia o {scale=10|10}%.", "card_cd": 0, "card_name_en": "Feed the Spirits"}, "L\u017cejsza tykwa": {"card_desc": "[Tykwa] Zwi\u0119ksza szybko\u015b\u0107 pocisku Tykwy o {scale=10|10}%.", "card_cd": 0, "card_name_en": "Lighter Gourd"}, "Op\u0119tanie": {"card_desc": "[Duchy naprawcze] Zmniejsza odnoszone przez ciebie obra\u017cenia o {scale=4|4}% podczas leczenia sojusznika przez Duchy naprawcze.", "card_cd": 0, "card_name_en": "Possession"}, "Pokonanie progu": {"card_desc": "[\u015alizg] Zwi\u0119ksza dystans pokonany przez \u015alizg o {scale=10|10}%.", "card_cd": 0, "card_name_en": "Liminal Passage"}, "Po\u017cywienie": {"card_desc": "[Pancerz] Zwi\u0119ksza otrzymywane leczenie o {scale=8|8}%, jak d\u0142ugo tw\u00f3j poziom zdrowia nie przekracza 50%.", "card_cd": 0, "card_name_en": "Sustenance"}, "Rytua\u0142 magiczny": {"card_desc": "[Duchy naprawcze] Przywraca {scale=15|15} PZ co 1 s podczas leczenia sojusznik\u00f3w przez Duchy naprawcze.", "card_cd": 0, "card_name_en": "Ritual Magic"}, "Tykwa za tykw\u0105": {"card_desc": "[Tykwa] Skraca czas odnowienia Tykwy o {scale=0.5|0.5} s.", "card_cd": 0, "card_name_en": "Many Gourds"}, "Ulotno\u015b\u0107": {"card_desc": "[\u015alizg] Skraca czas odnowienia \u015alizgu o {scale=0.6|0.6} s.", "card_cd": 0, "card_name_en": "Fleeting"}, "Upiorna obecno\u015b\u0107": {"card_desc": "[Duchy naprawcze] Redukuje czas odnowienia Duch\u00f3w naprawczych o {scale=0.5|0.5} s, je\u015bli oddany zostanie niecelny strza\u0142.", "card_cd": 0, "card_name_en": "Eerie Presence"}, "Wybraniec ducha": {"card_desc": "[Duchy naprawcze] Duchy naprawcze natychmiast przywracaj\u0105 twojemu celowi dodatkowe 200 PZ.", "card_cd": 0, "card_name_en": "Spirit's Chosen"}, "Wyostrzaj\u0105ca tykwa": {"card_desc": "[Tykwa] Aktywacja Tykwy przywraca {scale=75|75} PZ.", "card_cd": 0, "card_name_en": "Pungent Gourd"}, "Z za\u015bwiat\u00f3w": {"card_desc": "[\u015alizg] Zapewnia tarcz\u0119 o odporno\u015bci {scale=75|75} pkt. na 3 s po zako\u0144czeniu \u015alizgu.", "card_cd": 0, "card_name_en": "Otherworldly"}, "Zatrute tykwy": {"card_desc": "[Tykwa] Stanie w twojej Tykwie zapewnia tobie i sojusznikom {scale=6|6}% kradzie\u017cy \u017cycia.", "card_cd": 0, "card_name_en": "Venomous Gourd"}, "Zwinne duchy": {"card_desc": "[Duchy naprawcze] Zwi\u0119ksza szybko\u015b\u0107 ruchu sojusznik\u00f3w leczonych przez Duchy naprawcze o {scale=5|5}%.", "card_cd": 0, "card_name_en": "Swift Spirits"}}, "tr": {"Ba\u015fka D\u00fcnyadan": {"card_desc": "[Kayma] Kayma bittikten sonra 3sn boyunca {scale=75|75} Canl\u0131k bir Kalkan kazan.", "card_cd": 0, "card_name_en": "Otherworldly"}, "Destek": {"card_desc": "[Z\u0131rh] %50 Can veya alt\u0131ndayken ald\u0131\u011f\u0131n \u0130yile\u015ftirmeyi %{scale=8|8} art\u0131r.", "card_cd": 0, "card_name_en": "Sustenance"}, "Hafif Kabarc\u0131k": {"card_desc": "[Kabarc\u0131k] Kabarc\u0131k'\u0131n Mermi H\u0131z\u0131n\u0131 %{scale=10|10} art\u0131r.", "card_cd": 0, "card_name_en": "Lighter Gourd"}, "\u0130vedi Ruhlar": {"card_desc": "[\u0130yile\u015ftirici Ruhlar] \u0130yile\u015ftirici Ruhlar'dan etkilenen m\u00fcttefiklerin Hareket H\u0131z\u0131n\u0131 %{scale=5|5} art\u0131r.", "card_cd": 0, "card_name_en": "Swift Spirits"}, "Kabarc\u0131klar": {"card_desc": "[Kabarc\u0131k] Kabarc\u0131k'\u0131n Bekleme S\u00fcresini {scale=0.5|0.5}sn azalt.", "card_cd": 0, "card_name_en": "Many Gourds"}, "Ka\u00e7\u0131\u015f": {"card_desc": "[Kayma] Kayma'n\u0131n Bekleme S\u00fcresini {scale=0.6|0.6}sn azalt.", "card_cd": 0, "card_name_en": "Fleeting"}, "Olgun Kabarc\u0131k": {"card_desc": "[\u0130yile\u015ftirici Ruhlar] Kabarc\u0131k'\u0131n d\u00fc\u015fmanlara hasar vermez ancak iki kat daha fazla \u0130yile\u015ftirir.", "card_cd": 0, "card_name_en": "Ripened Gourd"}, "Ruhlar\u0131 Besle": {"card_desc": "[Z\u0131rh] Bir Saf D\u0131\u015f\u0131 B\u0131rakma yapt\u0131ktan sonra aktif Bekleme S\u00fcrelerini %{scale=10|10} azalt.", "card_cd": 0, "card_name_en": "Feed the Spirits"}, "Ruhlar\u0131n Kontrol\u00fcnde": {"card_desc": "[\u0130yile\u015ftirici Ruhlar] \u0130yile\u015ftirici Ruhlar ile bir m\u00fcttefiki iyile\u015ftirirken ald\u0131\u011f\u0131n hasar\u0131 %{scale=4|4} azalt.", "card_cd": 0, "card_name_en": "Possession"}, "Ruhun Dokunu\u015fu": {"card_desc": "[Kayma] Kayma kulland\u0131ktan sonra {scale=80|80} Can iyile\u015f.", "card_cd": 0, "card_name_en": "Spirit's Touch"}, "Se\u00e7ilmi\u015f Ruh": {"card_desc": "[\u0130yile\u015ftirici Ruhlar] \u0130yile\u015ftirici Ruhlar hedefini an\u0131nda ek 200 Can \u0130yile\u015ftirir.", "card_cd": 0, "card_name_en": "Spirit's Chosen"}, "S\u0131n\u0131rda Ge\u00e7i\u015f": {"card_desc": "[Kayma] Kayma ile kat etti\u011fin mesafeyi %{scale=10|10} art\u0131r.", "card_cd": 0, "card_name_en": "Liminal Passage"}, "Tekinsiz Varl\u0131k": {"card_desc": "[\u0130yile\u015ftirici Ruhlar] Iskalad\u0131\u011f\u0131nda \u0130yile\u015ftirici Ruhlar'\u0131n Bekleme S\u00fcresini {scale=0.5|0.5}sn azalt.", "card_cd": 0, "card_name_en": "Eerie Presence"}, "Tesirli Kabarc\u0131k": {"card_desc": "[Kabarc\u0131k] Kabarc\u0131k'\u0131 etkinle\u015ftirdikten sonra {scale=75|75} Can iyile\u015f.", "card_cd": 0, "card_name_en": "Pungent Gourd"}, "Tinsel": {"card_desc": "[Z\u0131rh] Maksimum Can\u0131n\u0131 {scale=50|50} art\u0131r.", "card_cd": 0, "card_name_en": "Incorporeal"}, "T\u00f6ren B\u00fcy\u00fcs\u00fc": {"card_desc": "[\u0130yile\u015ftirici Ruhlar] \u0130yile\u015ftirici Ruhlar ile bir m\u00fcttefiki iyile\u015ftirirken her 1 saniyede {scale=15|15} Can iyile\u015f.", "card_cd": 0, "card_name_en": "Ritual Magic"}, "Wekono'nun Gazab\u0131": {"card_desc": "[Silah] Yeniden doldurma sonras\u0131 y\u0131lan f\u0131rlatma h\u0131zlan\u0131r ve ek 500 hasar verir.", "card_cd": 0, "card_name_en": "Wekono's Wrath"}, "Y\u0131lan Yuvas\u0131": {"card_desc": "[Z\u0131rh] Hareket H\u0131z\u0131n\u0131 %{scale=2|2} art\u0131r.", "card_cd": 0, "card_name_en": "Snake Pit"}, "Zehirli Kabarc\u0131klar": {"card_desc": "[Kabarc\u0131k] Kabarc\u0131k'\u0131n\u0131n i\u00e7inde durmak sana ve m\u00fcttefiklerini %{scale=6|6} Can \u00c7alma verir.", "card_cd": 0, "card_name_en": "Venomous Gourd"}}}